CHANGES.txt
COPYRIGHT.txt
HOWTO_RELEASE.txt
LICENSE.txt
README.txt
bootstrap.py
buildout.cfg
setup.py
versions.cfg
scripts/changes.py
scripts/comparison_chart.py
src/bluebream/__init__.py
src/bluebream.egg-info/PKG-INFO
src/bluebream.egg-info/SOURCES.txt
src/bluebream.egg-info/dependency_links.txt
src/bluebream.egg-info/entry_points.txt
src/bluebream.egg-info/not-zip-safe
src/bluebream.egg-info/requires.txt
src/bluebream.egg-info/top_level.txt
src/bluebream/bluebream_base/__init__.py
src/bluebream/bluebream_base/paste_script_patch.py
src/bluebream/bluebream_base/template.py
src/bluebream/bluebream_base/project_template/README.txt_tmpl
src/bluebream/bluebream_base/project_template/bootstrap.py
src/bluebream/bluebream_base/project_template/buildout.cfg_tmpl
src/bluebream/bluebream_base/project_template/debug.ini_tmpl
src/bluebream/bluebream_base/project_template/deploy.ini_tmpl
src/bluebream/bluebream_base/project_template/setup.py_tmpl
src/bluebream/bluebream_base/project_template/etc/debug.zcml_tmpl
src/bluebream/bluebream_base/project_template/etc/deploy.zcml_tmpl
src/bluebream/bluebream_base/project_template/etc/zope-debug.conf
src/bluebream/bluebream_base/project_template/etc/zope-deploy.conf
src/bluebream/bluebream_base/project_template/extends-cache/README.txt
src/bluebream/bluebream_base/project_template/src/+package+/__init__.py
src/bluebream/bluebream_base/project_template/src/+package+/bluebream.zcml_tmpl
src/bluebream/bluebream_base/project_template/src/+package+/configure.zcml_tmpl
src/bluebream/bluebream_base/project_template/src/+package+/debug.py
src/bluebream/bluebream_base/project_template/src/+package+/overrides.zcml
src/bluebream/bluebream_base/project_template/src/+package+/securitypolicy.zcml_tmpl
src/bluebream/bluebream_base/project_template/src/+package+/startup.py
src/bluebream/bluebream_base/project_template/src/+package+/tests/__init__.py
src/bluebream/bluebream_base/project_template/src/+package+/tests/ftesting.zcml_tmpl
src/bluebream/bluebream_base/project_template/src/+package+/tests/tests.py_tmpl
src/bluebream/bluebream_base/project_template/src/+package+/welcome/__init__.py
src/bluebream/bluebream_base/project_template/src/+package+/welcome/app.py
