Metadata-Version: 1.0
Name: bluebream
Version: 1.0
Summary: The Zope Web Framework
Home-page: http://bluebream.zope.org
Author: Zope Foundation and Contributors
Author-email: bluebream@zope.org
License: ZPL
Platform: UNKNOWN
Classifier: Development Status :: 5 - Production/Stable
Classifier: Environment :: Web Environment
Classifier: Intended Audience :: Developers
Classifier: License :: OSI Approved :: Zope Public License
Classifier: Programming Language :: Python
Classifier: Framework :: Zope3
Classifier: Topic :: Internet :: WWW/HTTP
Classifier: Topic :: Internet :: WWW/HTTP :: WSGI
